BQ_radiomics/__init__.py
BQ_radiomics/common.py
BQ_radiomics/feature_reduction.py
BQ_radiomics/main.py
BQ_radiomics/monitor_memory.py
BQ_radiomics/normalise.py
BQ_radiomics/radiomics.py
BQ_radiomics/version.py
BQ_radiomics/scripts/__init__.py
BQ_radiomics/scripts/lama_machine_learning.py
BQ_radiomics/scripts/lama_radiomics_runner.py
Icube_radiomics-0.0.2.dist-info/METADATA
Icube_radiomics-0.0.2.dist-info/WHEEL
Icube_radiomics-0.0.2.dist-info/entry_points.txt
Icube_radiomics-0.0.2.dist-info/top_level.txt
Icube_radiomics-0.0.2.dist-info/RECORD
